posetta/__init__.py
posetta/__main__.py
posetta/data/__init__.py
posetta/data/coordset.py
posetta/data/coordset_meta.py
posetta/gui/__init__.py
posetta/gui/banner.png
posetta/gui/icon.png
posetta/gui/posetta_gui.py
posetta/gui/posetta_gui.pyi
posetta/gui/satellite.png
posetta/gui/stone.png
posetta/lib/__init__.py
posetta/lib/exceptions.py
posetta/lib/plugins.py
posetta/readers/__init__.py
posetta/readers/_reader.py
posetta/readers/_reader_line.py
posetta/readers/kml.py
posetta/readers/kms.py
posetta/readers/xyz.py
posetta/writers/__init__.py
posetta/writers/_writer.py
posetta/writers/csv.py
posetta/writers/proj.py
posetta-0.0.5.dist-info/entry_points.txt
posetta-0.0.5.dist-info/LICENSE
posetta-0.0.5.dist-info/WHEEL
posetta-0.0.5.dist-info/METADATA
posetta-0.0.5.dist-info/RECORD
