Metadata-Version: 2.1
Name: posetta
Version: 0.0.5
Summary: The Universal Translator of Geodetic Coordinate File Formats
Home-page: https://github.com/NordicGeodesy/posetta
License: MIT
Keywords: geodesy,coordinate,position,format,converter
Author: Nordic Geodetic Commision
Author-email: geir.arne.hjelle@kartverket.no
Requires-Python: >=3.6
Classifier: Development Status :: 2 - Pre-Alpha
Classifier: Intended Audience :: Science/Research
Classifier: License :: OSI Approved :: MIT License
Classifier: Natural Language :: English
Classifier: Operating System :: MacOS
Classifier: Operating System :: Microsoft
Classifier: Operating System :: POSIX :: Linux
Classifier: Programming Language :: Python :: 3
Classifier: Programming Language :: Python :: 3.6
Classifier: Programming Language :: Python :: 3.7
Classifier: Topic :: Scientific/Engineering
Requires-Dist: click (>=7.0)
Requires-Dist: fastkml (>=0.11.0)
Requires-Dist: lxml (>=4.2)
Requires-Dist: pandas (>=0.23.0)
